races/__init__.py
races/cli.py
races/models.py
races/parsers.py
races/report.py
monaco_racing_alexxstep-0.1.0.dist-info/METADATA
monaco_racing_alexxstep-0.1.0.dist-info/WHEEL
monaco_racing_alexxstep-0.1.0.dist-info/entry_points.txt
monaco_racing_alexxstep-0.1.0.dist-info/licenses/LICENSE
monaco_racing_alexxstep-0.1.0.dist-info/RECORD
