Metadata-Version: 2.4
Name: monaco-racing-alexxstep
Version: 0.1.0
Summary: Monaco 2018 Racing Q1 Report Generator
Project-URL: Homepage, https://github.com/alexxstep/task6-report-of-monaco-2018-racing
Project-URL: Repository, https://github.com/alexxstep/task6-report-of-monaco-2018-racing
Project-URL: Issues, https://github.com/alexxstep/task6-report-of-monaco-2018-racing/issues
Author-email: Oleksiy Stypanets <astep2004@gmail.com>
License: MIT
License-File: LICENSE
Keywords: cli,f1,formula1,monaco,qualification,racing,report
Classifier: Development Status :: 4 - Beta
Classifier: Environment :: Console
Classifier: Intended Audience :: Developers
Classifier: Intended Audience :: End Users/Desktop
Classifier: License :: OSI Approved :: MIT License
Classifier: Operating System :: OS Independent
Classifier: Programming Language :: Python :: 3
Classifier: Programming Language :: Python :: 3.9
Classifier: Programming Language :: Python :: 3.10
Classifier: Programming Language :: Python :: 3.11
Classifier: Programming Language :: Python :: 3.12
Classifier: Programming Language :: Python :: 3.13
Classifier: Topic :: Utilities
Requires-Python: >=3.9
Provides-Extra: dev
Requires-Dist: pytest-cov>=7.0.0; extra == 'dev'
Requires-Dist: pytest>=8.4.2; extra == 'dev'
Requires-Dist: ruff>=0.13.3; extra == 'dev'
